<annotation>
  <folder>VOC2007</folder>
  <filename>483.jpg</filename>
  <source>
    <database>My Database</database>
    <annotation>VOC2007</annotation>
    <image>flickr</image>
    <flickrid>NULL</flickrid>
  </source>
  <owner>
    <flickrid>NULL</flickrid>
    <name>idaneel</name>
  </owner>
  <size>
    <width>2560</width>
    <height>1440</height>
    <depth>3</depth>
  </size>
  <segmented>0</segmented>
  <object>
    <name>nail</name>
    <pose>Unspecified</pose>
    <truncated>0</truncated>
    <difficult>0</difficult>
    <bndbox>
      <xmin>1091</xmin>
      <ymin>422</ymin>
      <xmax>1169</xmax>
      <ymax>506</ymax>
    </bndbox>
  </object>
  <object>
    <name>clip_B</name>
    <pose>Unspecified</pose>
    <truncated>0</truncated>
    <difficult>0</difficult>
    <bndbox>
      <xmin>1295</xmin>
      <ymin>686</ymin>
      <xmax>1372</xmax>
      <ymax>762</ymax>
    </bndbox>
  </object>
  <object>
    <name>nail</name>
    <pose>Unspecified</pose>
    <truncated>0</truncated>
    <difficult>0</difficult>
    <bndbox>
      <xmin>1533</xmin>
      <ymin>565</ymin>
      <xmax>1584</xmax>
      <ymax>610</ymax>
    </bndbox>
  </object>
  <object>
    <name>nail</name>
    <pose>Unspecified</pose>
    <truncated>0</truncated>
    <difficult>0</difficult>
    <bndbox>
      <xmin>2007</xmin>
      <ymin>975</ymin>
      <xmax>2060</xmax>
      <ymax>1009</ymax>
    </bndbox>
  </object>
  <object>
    <name>clip_Y</name>
    <pose>Unspecified</pose>
    <truncated>0</truncated>
    <difficult>0</difficult>
    <bndbox>
      <xmin>1843</xmin>
      <ymin>1091</ymin>
      <xmax>1879</xmax>
      <ymax>1123</ymax>
    </bndbox>
  </object>
</annotation>
